{"type": "Feature", "id": 12513401, "geometry": {"type": "Point", "coordinates": [19.073, 47.180801]}, "properties": {"woe:id": 12513401, "woe:parent_id": 809825, "woe:name": "Kiskunlachaza Airport", "woe:placetype": 14, "woe:placetype_name": "Airport", "woe:lang": "ENG", "iso:country": "HU", "meta:provider": ["geoplanet:7.3.1", "geoplanet:7.3.2", "geoplanet:7.4.0", "geoplanet:7.4.1", "geoplanet:7.5.1", "geoplanet:7.5.2", "geoplanet:7.6.0", "geoplanet:7.8.1", "geoplanet:7.9.0", "geoplanet:7.10.0", "geoplanet:8.0.0", "woeplanet:8.0.0"], "meta:indexed": "2020-08-20T21:03:20.019119", "meta:updated": "2020-10-14T11:12:17.051246", "woe:hierarchy": {"continent": 24865675, "country": 23424844, "town": 0, "planet": 1, "county": 12593429, "suburb": 0, "state": 12577923, "region": 0, "localadmin": 0}, "woe:timezone_id": 28350893, "woe:hash": "u2ms6j0814g8", "woe:centroid": [19.073, 47.180801], "geom:latitude": 47.180801, "geom:longitude": 19.073, "geom:hash": "u2ms6j0814g8", "woe:latitude": 47.180801, "geom:centroid": [19.073, 47.180801], "woe:longitude": 19.073, "woe:repo": "woeplanet-airport-hu", "geom:area": 0.0, "woe:scale": 19}}