{"type": "Feature", "id": 12513407, "geometry": {"type": "Point", "coordinates": [18.1374, 46.169899]}, "properties": {"woe:id": 12513407, "woe:parent_id": 813211, "woe:name": "Mecsekrakos Airport", "woe:placetype": 14, "woe:placetype_name": "Airport", "woe:lang": "ENG", "iso:country": "HU", "meta:provider": ["geoplanet:7.3.1", "geoplanet:7.3.2", "geoplanet:7.4.0", "geoplanet:7.4.1", "geoplanet:7.5.1", "geoplanet:7.5.2", "geoplanet:7.6.0", "geoplanet:7.8.1", "geoplanet:7.9.0", "geoplanet:7.10.0", "geoplanet:8.0.0", "woeplanet:8.0.0"], "meta:indexed": "2020-08-20T21:03:20.023112", "meta:updated": "2020-10-14T11:12:17.046378", "woe:hierarchy": {"continent": 24865675, "country": 23424844, "town": 0, "planet": 1, "county": 12594102, "suburb": 0, "state": 12577912, "region": 0, "localadmin": 0}, "woe:timezone_id": 28350893, "woe:hash": "u2hysszr0hcx", "woe:centroid": [18.1374, 46.169899], "geom:latitude": 46.169899, "geom:longitude": 18.1374, "geom:hash": "u2hysszr0hcx", "woe:latitude": 46.169899, "geom:centroid": [18.1374, 46.169899], "woe:longitude": 18.1374, "woe:repo": "woeplanet-airport-hu", "geom:area": 0.0, "woe:scale": 19}}