{"type": "Feature", "id": 12513404, "geometry": {"type": "Point", "coordinates": [20.401501, 46.2341]}, "properties": {"woe:id": 12513404, "woe:parent_id": 811437, "woe:name": "Kortyogo Airport", "woe:placetype": 14, "woe:placetype_name": "Airport", "woe:lang": "ENG", "iso:country": "HU", "meta:provider": ["geoplanet:7.3.1", "geoplanet:7.3.2", "geoplanet:7.4.0", "geoplanet:7.4.1", "geoplanet:7.5.1", "geoplanet:7.5.2", "geoplanet:7.6.0", "geoplanet:7.8.1", "geoplanet:7.9.0", "geoplanet:7.10.0", "geoplanet:8.0.0", "woeplanet:8.0.0"], "meta:indexed": "2020-08-20T21:03:20.021039", "meta:updated": "2020-10-14T11:12:17.039444", "woe:hierarchy": {"continent": 24865675, "country": 23424844, "town": 0, "planet": 1, "county": 12593817, "suburb": 0, "state": 12577916, "region": 0, "localadmin": 0}, "woe:timezone_id": 28350893, "woe:hash": "u2nx00xvjkvt", "woe:centroid": [20.401501, 46.2341], "geom:latitude": 46.2341, "geom:longitude": 20.401501, "geom:hash": "u2nx00xvjkvt", "woe:latitude": 46.2341, "geom:centroid": [20.401501, 46.2341], "woe:longitude": 20.401501, "woe:repo": "woeplanet-airport-hu", "geom:area": 0.0, "woe:scale": 19}}