{"type": "Feature", "id": 12513395, "properties": {"woe:id": 12513395, "woe:parent_id": 812864, "woe:name": "Hejokeresztur Airport", "woe:placetype": 14, "woe:placetype_name": "Airport", "woe:lang": "ENG", "iso:country": "HU", "meta:provider": ["geoplanet:7.3.1", "geoplanet:7.3.2", "geoplanet:7.4.0", "geoplanet:7.4.1", "geoplanet:7.5.1", "geoplanet:7.5.2", "geoplanet:7.6.0", "geoplanet:7.8.1", "geoplanet:7.9.0", "geoplanet:7.10.0", "geoplanet:8.0.0", "woeplanet:8.0.0"], "meta:indexed": "2020-08-20T21:03:20.015209", "meta:updated": "2020-08-22T01:54:38.725658", "woe:hierarchy": {"continent": 24865675, "country": 23424844, "town": 0, "planet": 1, "county": 12595753, "suburb": 0, "state": 12577914, "region": 0, "localadmin": 0}, "woe:timezone_id": 28350893, "woe:hash": "u2wbftrd3nug", "woe:centroid": [20.8624, 47.973598], "geom:latitude": 47.973598, "geom:longitude": 20.8624, "geom:hash": "u2wbftrd3nug", "woe:latitude": 47.973598, "geom:centroid": [20.8624, 47.973598], "woe:longitude": 20.8624, "woe:repo": "woeplanet-airport-hu"}, "geometry": {"coordinates": [20.8624, 47.973598], "type": "Point"}}